nameseer/__init__.py
nameseer/experiment.py
nameseer/name_classifier.py
nameseer/nameseer_meta.pk
nameseer/nameseer_model.pk
nameseer/nameseer_vec.pk
nameseer/__pycache__/__init__.cpython-38.pyc
nameseer/__pycache__/__init__.cpython-39.pyc
nameseer/__pycache__/experiment.cpython-38.pyc
nameseer/__pycache__/experiment.cpython-39.pyc
nameseer/__pycache__/name_classifier.cpython-38.pyc
nameseer/__pycache__/name_classifier.cpython-39.pyc
nameseer-0.1.4.dist-info/LICENSE
nameseer-0.1.4.dist-info/METADATA
nameseer-0.1.4.dist-info/WHEEL
nameseer-0.1.4.dist-info/top_level.txt
nameseer-0.1.4.dist-info/RECORD
